seymourlib/__init__.py
seymourlib/cli.py
seymourlib/client.py
seymourlib/discovery.py
seymourlib/exceptions.py
seymourlib/protocol.py
seymourlib/py.typed
seymourlib/transport.py
seymourlib-0.1.4.dist-info/licenses/LICENSE
seymourlib-0.1.4.dist-info/WHEEL
seymourlib-0.1.4.dist-info/entry_points.txt
seymourlib-0.1.4.dist-info/METADATA
seymourlib-0.1.4.dist-info/RECORD
