Metadata-Version: 2.4
Name: seymourlib
Version: 0.1.4
Summary: Python client for Seymour masking screens, connected via direct serial or Global Caché iTach IP2SL
Keywords: seymour,masking,screen,serial,itach,ip2sl,home-assistant
Author: Richard Berg
Author-email: Richard Berg <ars@richardberg.net>
License-Expression: MIT
License-File: LICENSE
Classifier: Development Status :: 3 - Alpha
Classifier: Intended Audience :: Developers
Classifier: Programming Language :: Python :: 3 :: Only
Classifier: Programming Language :: Python :: 3.11
Classifier: Programming Language :: Python :: 3.12
Classifier: Topic :: Home Automation
Requires-Dist: anyio>=3.4
Requires-Dist: attrs>=25.4.0
Requires-Dist: tenacity>=8.0
Requires-Dist: async-typer>=0.1.10
Requires-Dist: pyserial-asyncio>=0.6 ; extra == 'serial'
Requires-Python: >=3.11
Project-URL: homepage, https://github.com/richard-berg/seymourlib
Project-URL: issues, https://github.com/richard-berg/seymourlib/issues
Project-URL: source, https://github.com/richard-berg/seymourlib.git
Provides-Extra: serial
